ebsfm/__init__.py
ebsfm_schedule-0.0.3.dist-info/LICENSE
ebsfm_schedule-0.0.3.dist-info/METADATA
ebsfm_schedule-0.0.3.dist-info/WHEEL
ebsfm_schedule-0.0.3.dist-info/top_level.txt
ebsfm_schedule-0.0.3.dist-info/RECORD
